ff3/__init__.py
ff3/__main__.py
ff3/ff3.py
ff3/ff3_perf.py
ff3/ff3_test.py
ff3-1.0.3.dist-info/licenses/LICENSE
ff3-1.0.3.dist-info/METADATA
ff3-1.0.3.dist-info/WHEEL
ff3-1.0.3.dist-info/entry_points.txt
ff3-1.0.3.dist-info/top_level.txt
ff3-1.0.3.dist-info/RECORD
